sparkstart-0.1.2.dist-info/METADATA
sparkstart-0.1.2.dist-info/WHEEL
sparkstart-0.1.2.dist-info/entry_points.txt
sparkstart/__init__.py
sparkstart/cli.py
sparkstart/core.py
sparkstart-0.1.2.dist-info/RECORD
