Metadata-Version: 2.1
Name: sparkstart
Version: 0.1.2
Summary: Spin-up a ready-to-code project with one command
Author-Email: Jordan Longval <majorlongval@gmail.com>
Requires-Python: >=3.8
Requires-Dist: typer
Requires-Dist: requests
Requires-Dist: python-dotenv
